experimented/__init__.py
experimented/experiment_management.py
experimented-0.0.7.dist-info/METADATA
experimented-0.0.7.dist-info/WHEEL
experimented-0.0.7.dist-info/entry_points.txt
experimented-0.0.7.dist-info/top_level.txt
experimented-0.0.7.dist-info/RECORD
