Metadata-Version: 2.4
Name: experimented
Version: 0.0.7
Summary: Experiment store.
Author-email: Baichuan Li <baichuanli@yahoo.com>
License: MIT
Project-URL: Homepage, https://github.com/Gorgeous-Patrick/experimented
Requires-Python: >=3.9
Requires-Dist: typer>=0.19
Requires-Dist: pydantic>=2.9
